gender_predictor_module/__init__.py
gender_predictor_module/model_utils.py
gender_predictor_by_rp-0.1.2.dist-info/METADATA
gender_predictor_by_rp-0.1.2.dist-info/WHEEL
gender_predictor_by_rp-0.1.2.dist-info/top_level.txt
gender_predictor_by_rp-0.1.2.dist-info/RECORD
