Metadata-Version: 2.4
Name: gender_predictor_by_rp
Version: 0.1.2
Summary: Gender prediction from names using a trained ML model
Author: Rahul Patel
Classifier: Programming Language :: Python :: 3
Requires-Dist: keras
Requires-Dist: tensorflow
Dynamic: author
Dynamic: classifier
Dynamic: description
Dynamic: description-content-type
Dynamic: requires-dist
Dynamic: summary
